softpack_core/__init__.py
softpack_core/api.py
softpack_core/app.py
softpack_core/artifacts.py
softpack_core/config/conf/config.yml
softpack_core/config/models.py
softpack_core/config/settings.py
softpack_core/graphql.py
softpack_core/ldapapi.py
softpack_core/main.py
softpack_core/schemas/base.py
softpack_core/schemas/environment.py
softpack_core/schemas/package_collection.py
softpack_core/service.py
softpack_core/spack.py
softpack_core/url.py
softpack_core-0.1.0.dist-info/LICENSE
softpack_core-0.1.0.dist-info/METADATA
softpack_core-0.1.0.dist-info/WHEEL
softpack_core-0.1.0.dist-info/entry_points.txt
softpack_core-0.1.0.dist-info/RECORD
