Metadata-Version: 2.1
Name: softpack-core
Version: 0.1.0
Summary: SoftPack Core backend service.
Home-page: https://github.com/wtsi-hgi/softpack-core
License: MIT
Author: altaf-ali
Author-email: altaf.ali@sanger.ac.uk
Requires-Python: >=3.9,<4.0
Classifier: Development Status :: 2 - Pre-Alpha
Classifier: Intended Audience :: Developers
Classifier: License :: OSI Approved :: MIT License
Classifier: Natural Language :: English
Classifier: Programming Language :: Python :: 3
Classifier: Programming Language :: Python :: 3.9
Classifier: Programming Language :: Python :: 3.10
Classifier: Programming Language :: Python :: 3.11
Requires-Dist: archspec (>=0.2.0,<0.3.0)
Requires-Dist: bokeh (>=2.4.3,<3.0)
Requires-Dist: fastapi (>=0.94.0,<0.95.0)
Requires-Dist: greenlet (>=2.0.2,<3.0.0)
Requires-Dist: hvac (>=1.1.0,<2.0.0)
Requires-Dist: jinja2 (>=3.1.2,<4.0.0)
Requires-Dist: macholib (>=1.16.2,<2.0.0)
Requires-Dist: mergedeep (>=1.3.4,<2.0.0)
Requires-Dist: oras (>=0.1.17,<0.2.0)
Requires-Dist: pip (>=23.0.1,<24.0.0)
Requires-Dist: prefect (==2.8.6)
Requires-Dist: prefect-dask (>=0.2.3,<0.3.0)
Requires-Dist: prefect-shell (>=0.1.5,<0.2.0)
Requires-Dist: pydantic (>=1.10.6,<2.0.0)
Requires-Dist: pygit2 (>=1.12.1,<2.0.0)
Requires-Dist: python-box (>=7.0.1,<8.0.0)
Requires-Dist: python-ldap (>=3.4.3,<4.0.0)
Requires-Dist: requests (<2.30.0)
Requires-Dist: ruamel-yaml (>=0.17.21,<0.18.0)
Requires-Dist: semver (>=3.0.0,<4.0.0)
Requires-Dist: singleton-decorator (>=1.0.0,<2.0.0)
Requires-Dist: sqlalchemy (==1.4.45)
Requires-Dist: strawberry-graphql (>=0.177.1,<0.178.0)
Requires-Dist: typer (>=0.9.0,<0.10.0)
